collective.ploneboard-1.0.0a1-py2.7-nspkg.pth
collective/ploneboard/__init__.py
collective/ploneboard/configure.zcml
collective/ploneboard/interfaces.py
collective/ploneboard/permissions.zcml
collective/ploneboard/setuphandlers.py
collective/ploneboard/testing.py
collective/ploneboard/browser/__init__.py
collective/ploneboard/browser/commentextender.py
collective/ploneboard/browser/configure.zcml
collective/ploneboard/browser/messageboard.pt
collective/ploneboard/browser/messageboard.py
collective/ploneboard/browser/topic.pt
collective/ploneboard/browser/topic.py
collective/ploneboard/locales/collective.ploneboard.pot
collective/ploneboard/locales/de/LC_MESSAGES/collective.ploneboard.po
collective/ploneboard/overrides/plone.app.discussion.browser.comments.pt
collective/ploneboard/profiles/default/cssregistry.xml
collective/ploneboard/profiles/default/metadata.xml
collective/ploneboard/profiles/default/registry.xml
collective/ploneboard/profiles/default/types.xml
collective/ploneboard/profiles/default/types/Conversation.xml
collective/ploneboard/profiles/default/types/Message_Board.xml
collective/ploneboard/profiles/default/types/Topic.xml
collective/ploneboard/profiles/uninstall/browserlayer.xml
collective/ploneboard/static/images/conversation.gif
collective/ploneboard/static/images/new_conversation.gif
collective/ploneboard/static/images/ploneboard.gif
collective/ploneboard/static/stylesheets/ploneboard.css
collective/ploneboard/tests/__init__.py
collective/ploneboard/tests/image.png
collective/ploneboard/tests/test_conversation.py
collective/ploneboard/tests/test_functional.py
collective/ploneboard/tests/test_integration.py
collective/ploneboard/tests/test_messageboard.py
collective/ploneboard/tests/test_setup.py
collective/ploneboard/tests/test_topic.py
collective.ploneboard-1.0.0a1.dist-info/METADATA
collective.ploneboard-1.0.0a1.dist-info/WHEEL
collective.ploneboard-1.0.0a1.dist-info/entry_points.txt
collective.ploneboard-1.0.0a1.dist-info/namespace_packages.txt
collective.ploneboard-1.0.0a1.dist-info/paster_plugins.txt
collective.ploneboard-1.0.0a1.dist-info/top_level.txt
collective.ploneboard-1.0.0a1.dist-info/RECORD
