Metadata-Version: 2.1
Name: collective.ploneboard
Version: 1.0.0a1
Summary: Web board for the Plone Content Management System
Home-page: http://github.com/collective/collective.ploneboard/
Author: kitconcept GmbH
Author-email: info@kitconcept.com
License: gpl
Keywords: plone web board collaboration
Platform: UNKNOWN
Classifier: Environment :: Web Environment
Classifier: Framework :: Plone
Classifier: Framework :: Plone :: 5.0
Classifier: Framework :: Plone :: 5.1
Classifier: Operating System :: OS Independent
Classifier: Programming Language :: Python
Classifier: Programming Language :: Python :: 2.7
Classifier: Topic :: Software Development :: Libraries :: Python Modules
Requires-Dist: setuptools
Requires-Dist: plone.api
Requires-Dist: plone.app.dexterity
Requires-Dist: plone.directives.form
Requires-Dist: plone.namedfile[blobs]
Requires-Dist: z3c.jbot
Provides-Extra: test
Requires-Dist: plone.app.testing ; extra == 'test'
